apyds_egg/__init__.py
apyds_egg/py.typed
apyds_egg-0.0.14.dist-info/METADATA
apyds_egg-0.0.14.dist-info/WHEEL
apyds_egg-0.0.14.dist-info/top_level.txt
apyds_egg-0.0.14.dist-info/RECORD
